{
  "membre": [
    {
      "id": "1",
      "nom": "zahdi",
      "prenom": "Mansour",
      "numero": "27852654",
      "email": "membre1@enicar.uncar.tn",
      "isLibre": true,
      "imgSrc": "../../../../../assets/images/Placeholder/blank-profile-picture.png",
      "comite": "LOGISTIQUE"
    },
    {
      "id": "2",
      "nom": "Amine chograni",
      "prenom": "Mohamed",
      "numero": "27872654",
      "email": "membre2@enicar.ucar.tn",
      "isLibre": true,
      "imgSrc": "../../../../../assets/images/Placeholder/blank-profile-picture.png",
      "comite": "MEDIA"
    },
    {
      "id": "3",
      "nom": "rebaii",
      "prenom": "Saber",
      "numero": "2266544",
      "email": "membre3@enicar.ucar.tn",
      "isLibre": true,
      "imgSrc": "../../../../../assets/images/Placeholder/blank-profile-picture.png",
      "comite": "SPONSORING"
    },
    {
      "id": "5",
      "nom": "mehdi",
      "prenom": "salhi",
      "numero": "912654",
      "email": "membre3@enicar.ucar.tn",
      "isLibre": true,
      "imgSrc": "../../../../../assets/images/Placeholder/blank-profile-picture.png",
      "comite": "SPONSORING"
    }
  ]
}